zas_rep_tools_data/utils.py
zas_rep_tools_data-0.3.dist-info/LICENSE
zas_rep_tools_data-0.3.dist-info/METADATA
zas_rep_tools_data-0.3.dist-info/WHEEL
zas_rep_tools_data-0.3.dist-info/top_level.txt
zas_rep_tools_data-0.3.dist-info/RECORD
