Metadata-Version: 2.1
Name: zas-rep-tools-data
Version: 0.3
Summary: This is the data-set for "zas-rep-tools" package.
Home-page: https://github.com/savin-berlin/zas-rep-tools-data
Author: Egor Savin
Author-email: science@savin.berlin
License: MIT
Platform: UNKNOWN
Classifier: Development Status :: 1 - Planning
Classifier: Intended Audience :: Science/Research
Classifier: License :: OSI Approved :: MIT License
Classifier: Programming Language :: Python :: 2.7
Classifier: Operating System :: MacOS :: MacOS X
Classifier: Operating System :: Microsoft :: Windows :: Windows 10
Classifier: Operating System :: Unix
Classifier: Programming Language :: Java
Classifier: Programming Language :: Python :: 3
Classifier: Topic :: Scientific/Engineering :: Information Analysis
Classifier: Topic :: Text Processing :: Linguistic
